petabvis/__init__.py
petabvis/bar_plot.py
petabvis/bar_row.py
petabvis/dotted_line.py
petabvis/main.py
petabvis/plot_class.py
petabvis/plot_row.py
petabvis/row_class.py
petabvis/table_models.py
petabvis/utils.py
petabvis/version.py
petabvis/vis_spec_plot.py
petabvis/window_functionality.py
petabvis-0.0.2.dist-info/LICENSE
petabvis-0.0.2.dist-info/METADATA
petabvis-0.0.2.dist-info/WHEEL
petabvis-0.0.2.dist-info/entry_points.txt
petabvis-0.0.2.dist-info/top_level.txt
petabvis-0.0.2.dist-info/RECORD
