Metadata-Version: 2.1
Name: petabvis
Version: 0.0.2
Summary: Interactive visualization of PEtab problems
Home-page: https://github.com/PEtab-dev/petabvis
Maintainer: Dilan Pathirana, Daniel Weindl
Maintainer-email: dilan.pathirana@uni-bonn.de, daniel.weindl@helmholtz-muenchen.de
License: BSD-3-Clause License
Project-URL: Bug Reports, https://github.com/PEtab-dev/petabvis/issues
Project-URL: Source, https://github.com/PEtab-dev/petabvis
Keywords: petab,visualization
Platform: UNKNOWN
Classifier: Development Status :: 3 - Alpha
Classifier: License :: OSI Approved :: BSD License
Requires-Python: <4,>=3.7
Requires-Dist: pandas (>=1.2.1)
Requires-Dist: petab (>=0.1.14)
Requires-Dist: PySide2 (>=5.15.1)
Requires-Dist: PyYAML (>=5.3.1)
Requires-Dist: pyqtgraph (>=0.11.0)
Requires-Dist: scipy (>=1.5.0)
Requires-Dist: numpy (>=1.19)
